pymunk/__init__.py
pymunk/_callbacks.py
pymunk/_chipmunk.pypy311-pp73-aarch64-linux-gnu.so
pymunk/_chipmunk_cffi.py
pymunk/_collision_handler.py
pymunk/_pickle.py
pymunk/_pyglet15_util.py
pymunk/_types.py
pymunk/_typing_attr.py
pymunk/_util.py
pymunk/_version.py
pymunk/_weakkeysview.py
pymunk/arbiter.py
pymunk/autogeometry.py
pymunk/batch.py
pymunk/bb.py
pymunk/body.py
pymunk/constraints.py
pymunk/contact_point_set.py
pymunk/matplotlib_util.py
pymunk/py.typed
pymunk/pygame_util.py
pymunk/pyglet_util.py
pymunk/pymunk_extension_build.py
pymunk/query_info.py
pymunk/shape_filter.py
pymunk/shapes.py
pymunk/space.py
pymunk/space_debug_draw_options.py
pymunk/transform.py
pymunk/util.py
pymunk/vec2d.py
pymunk/examples/__init__.py
pymunk/examples/__main__.py
pymunk/examples/arrows.py
pymunk/examples/balls_and_lines.py
pymunk/examples/basic_test.py
pymunk/examples/bouncing_balls.py
pymunk/examples/box2d_pyramid.py
pymunk/examples/box2d_vertical_stack.py
pymunk/examples/breakout.py
pymunk/examples/camera.py
pymunk/examples/collisions.py
pymunk/examples/colors.py
pymunk/examples/colors_pyglet_batch.py
pymunk/examples/constraints.py
pymunk/examples/contact_and_no_flipy.py
pymunk/examples/contact_with_friction.py
pymunk/examples/copy_and_pickle.py
pymunk/examples/damped_rotary_spring_pointer.py
pymunk/examples/deformable.py
pymunk/examples/flipper.py
pymunk/examples/index_video.py
pymunk/examples/matplotlib_util_demo.py
pymunk/examples/newtons_cradle.py
pymunk/examples/planet.py
pymunk/examples/platformer.py
pymunk/examples/playground.py
pymunk/examples/point_query.py
pymunk/examples/pygame_util_demo.py
pymunk/examples/pyglet_util_demo.py
pymunk/examples/pymunk_logo_googlecode.png
pymunk/examples/pymunk_logo_sphinx.png
pymunk/examples/sfx.wav
pymunk/examples/shapes_for_draw_demos.py
pymunk/examples/slide_and_pinjoint.py
pymunk/examples/spiderweb.py
pymunk/examples/tank.py
pymunk/examples/threaded_space.py
pymunk-7.1.0.dist-info/METADATA
pymunk-7.1.0.dist-info/WHEEL
pymunk-7.1.0.dist-info/top_level.txt
pymunk-7.1.0.dist-info/RECORD
pymunk-7.1.0.dist-info/licenses/LICENSE.txt
