Metadata-Version: 2.4
Name: pymunk
Version: 7.1.0
Summary: Pymunk is a easy-to-use pythonic 2D physics library
Author-email: Victor Blomqvist <vb@viblo.se>
License-Expression: MIT
Project-URL: Homepage, https://www.pymunk.org
Project-URL: Documentation, https://www.pymunk.org
Project-URL: Repository, https://github.com/viblo/pymunk.git
Project-URL: Issues, https://github.com/viblo/viblo/issues
Project-URL: Changelog, https://github.com/viblo/pymunk/blob/master/CHANGELOG.rst
Keywords: pygame,2d,physics,rigid body
Classifier: Development Status :: 5 - Production/Stable
Classifier: Intended Audience :: Developers
Classifier: Operating System :: OS Independent
Classifier: Topic :: Games/Entertainment
Classifier: Topic :: Software Development :: Libraries
Classifier: Topic :: Software Development :: Libraries :: pygame
Classifier: Topic :: Scientific/Engineering :: Physics
Classifier: Programming Language :: Python
Classifier: Programming Language :: Python :: 3
Requires-Python: >=3.9
License-File: LICENSE.txt
Requires-Dist: cffi>=1.17.1; platform_system != "Emscripten"
Requires-Dist: cffi>1.14.0; platform_system == "Emscripten"
Provides-Extra: dev
Requires-Dist: pyglet; extra == "dev"
Requires-Dist: pygame; extra == "dev"
Requires-Dist: sphinx; extra == "dev"
Requires-Dist: aafigure; extra == "dev"
Requires-Dist: wheel; extra == "dev"
Requires-Dist: matplotlib; extra == "dev"
Requires-Dist: numpy; extra == "dev"
Dynamic: license-file
